pickley/__init__.py
pickley/__main__.py
pickley/bstrap.py
pickley/cli.py
pickley/delivery.py
pickley/package.py
pickley-4.5.9.dist-info/licenses/LICENSE
pickley-4.5.9.dist-info/METADATA
pickley-4.5.9.dist-info/WHEEL
pickley-4.5.9.dist-info/entry_points.txt
pickley-4.5.9.dist-info/top_level.txt
pickley-4.5.9.dist-info/RECORD
